scyllabackup/__init__.py
scyllabackup/cli.py
scyllabackup/db.py
scyllabackup/migrate.py
scyllabackup/snapshot.py
scyllabackup-0.1.0.dist-info/METADATA
scyllabackup-0.1.0.dist-info/RECORD
scyllabackup-0.1.0.dist-info/WHEEL
scyllabackup-0.1.0.dist-info/entry_points.txt
scyllabackup-0.1.0.dist-info/top_level.txt
