Metadata-Version: 2.1
Name: scyllabackup
Version: 0.1.0
Summary: Scyllabackup: A tool for taking scylla backups
Home-page: https://github.com/helpshift/scyllabackup
License: MIT License
Platform: UNKNOWN
Requires-Dist: spongeblob (==0.1.1)
Requires-Dist: tenacity (==4.10.0)
Requires-Dist: sh (==1.12.14)
Requires-Dist: gevent (==1.2.2)
Requires-Dist: ConfigArgParse (==0.13.0)
Requires-Dist: filelock (==3.0.4)
